{
  "auth": {
    "email": "ant@design.com",
    "password": "12345678"
  },
  "users": {
    "meta": {
      "total": 2,
      "per_page": 1,
      "page": 1
    },
    "data": [{
      "id": 1,
      "email": "john@doe.com",
      "name": "John Doe",
      "roles": "admin",
      "created_at": "2016-08-13 15:45:08 GTM+0200"
    },
    {
      "id": 2,
      "email": "jane@doe.com",
      "name": "Jane Doe",
      "roles": "user",
      "created_at": "2016-08-13 15:50:32 GTM+0200"
    }]
  },
  "menus": [
    {
      "name": "home",
      "url": "home",
      "icon": "home"
    },
    {
      "name": "activity log",
      "url": "operation_log",
      "icon": "operation_log"
    }

  ]
}
